{
	"backtrace" : 0,
	"backtraceGraph" : 
	{
		"commands" : [],
		"files" : 
		[
			"Vendor/fmt/CMakeLists.txt"
		],
		"nodes" : 
		[
			{
				"file" : 0
			}
		]
	},
	"dependencies" : 
	[
		{
			"id" : "fmt::@5d8f49674edd15c760ad"
		},
		{
			"id" : "ZERO_CHECK::@6890427a1f51a3e7e1df"
		}
	],
	"folder" : 
	{
		"name" : "CMakePredefinedTargets"
	},
	"id" : "ALL_BUILD::@5d8f49674edd15c760ad",
	"isGeneratorProvided" : true,
	"name" : "ALL_BUILD",
	"paths" : 
	{
		"build" : "Vendor/fmt",
		"source" : "Vendor/fmt"
	},
	"sources" : [],
	"type" : "UTILITY"
}
